{
	"SDSS-II SN 20646":{
		"schema":"https://github.com/astrocatalogs/astrocats/blob/aaf96e3b3fbcf703610b756295a7120ec1ecc3f7/OSC-JSON-format.md",
		"name":"SDSS-II SN 20646",
		"sources":[
			{
				"name":"2014arXiv1401.3317S",
				"bibcode":"2014arXiv1401.3317S",
				"reference":"Sako et al. (2014)",
				"url":"http://data.sdss3.org/sas/dr10/boss/papers/supernova/",
				"alias":"1"
			},
			{
				"name":"2011ApJ...737..103S",
				"bibcode":"2011ApJ...737..103S",
				"reference":"Schlafly & Finkbeiner (2011)",
				"alias":"2"
			},
			{
				"name":"The Open Supernova Catalog",
				"bibcode":"2016arXiv160501054G",
				"reference":"Guillochon, Parrent, & Margutti (2016)",
				"secondary":true,
				"url":"https://sne.space",
				"alias":"3"
			}
		],
		"alias":[
			{
				"value":"SDSS-II SN 20646",
				"source":"1"
			}
		],
		"claimedtype":[
			{
				"value":"II",
				"source":"1"
			}
		],
		"dec":[
			{
				"value":"+00:49:52.871",
				"u_value":"degrees",
				"source":"1"
			},
			{
				"value":"+00:49:52.518",
				"u_value":"degrees",
				"source":"1"
			}
		],
		"discoverdate":[
			{
				"value":"2007/09/03",
				"derived":true,
				"source":"1,3"
			}
		],
		"ebv":[
			{
				"value":"0.0553",
				"derived":true,
				"e_value":"0.0025",
				"source":"2,3"
			}
		],
		"host":[
			{
				"value":"SDSS J14423.79+004952.8",
				"source":"1"
			}
		],
		"hostdec":[
			{
				"value":"+00:49:52.8384",
				"u_value":"degrees",
				"source":"1"
			}
		],
		"hostoffsetang":[
			{
				"value":"0.0326",
				"derived":true,
				"u_value":"arcseconds",
				"source":"1,3"
			}
		],
		"hostra":[
			{
				"value":"21:44:23.76",
				"u_value":"hours",
				"source":"1"
			}
		],
		"maxappmag":[
			{
				"value":"20.84",
				"derived":true,
				"source":"1,3"
			}
		],
		"maxband":[
			{
				"value":"z'",
				"derived":true,
				"source":"1,3"
			}
		],
		"maxdate":[
			{
				"value":"2007/11/17",
				"derived":true,
				"source":"1,3"
			}
		],
		"ra":[
			{
				"value":"21:44:23.76",
				"u_value":"hours",
				"source":"1"
			}
		],
		"photometry":[
			{
				"time":"54346.197413",
				"band":"r'",
				"e_magnitude":"0.591",
				"magnitude":"23.494",
				"system":"SDSS",
				"telescope":"SDSS",
				"u_time":"MJD",
				"source":"1"
			},
			{
				"time":"54346.198242",
				"band":"i'",
				"e_magnitude":"0.463",
				"magnitude":"22.656",
				"system":"SDSS",
				"telescope":"SDSS",
				"u_time":"MJD",
				"source":"1"
			},
			{
				"time":"54346.199901",
				"band":"z'",
				"e_magnitude":"0.774",
				"magnitude":"21.715",
				"system":"SDSS",
				"telescope":"SDSS",
				"u_time":"MJD",
				"source":"1"
			},
			{
				"time":"54356.238556",
				"band":"r'",
				"e_magnitude":"0.398",
				"magnitude":"22.950",
				"system":"SDSS",
				"telescope":"SDSS",
				"u_time":"MJD",
				"source":"1"
			},
			{
				"time":"54356.239385",
				"band":"i'",
				"e_magnitude":"0.883",
				"magnitude":"23.502",
				"system":"SDSS",
				"telescope":"SDSS",
				"u_time":"MJD",
				"source":"1"
			},
			{
				"time":"54356.240214",
				"band":"u'",
				"e_magnitude":"1.276",
				"magnitude":"24.071",
				"system":"SDSS",
				"telescope":"SDSS",
				"u_time":"MJD",
				"source":"1"
			},
			{
				"time":"54356.241044",
				"band":"z'",
				"e_magnitude":"0.763",
				"magnitude":"22.915",
				"system":"SDSS",
				"telescope":"SDSS",
				"u_time":"MJD",
				"source":"1"
			},
			{
				"time":"54356.241873",
				"band":"g'",
				"e_magnitude":"0.343",
				"magnitude":"23.291",
				"system":"SDSS",
				"telescope":"SDSS",
				"u_time":"MJD",
				"source":"1"
			},
			{
				"time":"54358.184274",
				"band":"i'",
				"e_magnitude":"0.740",
				"magnitude":"22.782",
				"system":"SDSS",
				"telescope":"SDSS",
				"u_time":"MJD",
				"source":"1"
			},
			{
				"time":"54358.185932",
				"band":"z'",
				"e_magnitude":"0.729",
				"magnitude":"23.698",
				"system":"SDSS",
				"telescope":"SDSS",
				"u_time":"MJD",
				"source":"1"
			},
			{
				"time":"54358.186761",
				"band":"g'",
				"e_magnitude":"0.262",
				"magnitude":"22.710",
				"system":"SDSS",
				"telescope":"SDSS",
				"u_time":"MJD",
				"source":"1"
			},
			{
				"time":"54359.149551",
				"band":"r'",
				"e_magnitude":"0.836",
				"magnitude":"23.606",
				"system":"SDSS",
				"telescope":"SDSS",
				"u_time":"MJD",
				"source":"1"
			},
			{
				"time":"54359.150381",
				"band":"i'",
				"e_magnitude":"0.958",
				"magnitude":"23.453",
				"system":"SDSS",
				"telescope":"SDSS",
				"u_time":"MJD",
				"source":"1"
			},
			{
				"time":"54359.151210",
				"band":"u'",
				"e_magnitude":"0.742",
				"magnitude":"22.736",
				"system":"SDSS",
				"telescope":"SDSS",
				"u_time":"MJD",
				"source":"1"
			},
			{
				"time":"54359.152039",
				"band":"z'",
				"e_magnitude":"0.423",
				"magnitude":"24.404",
				"system":"SDSS",
				"telescope":"SDSS",
				"u_time":"MJD",
				"source":"1"
			},
			{
				"time":"54359.152868",
				"band":"g'",
				"e_magnitude":"0.283",
				"magnitude":"22.936",
				"system":"SDSS",
				"telescope":"SDSS",
				"u_time":"MJD",
				"source":"1"
			},
			{
				"time":"54373.214889",
				"band":"r'",
				"e_magnitude":"0.498",
				"magnitude":"22.922",
				"system":"SDSS",
				"telescope":"SDSS",
				"u_time":"MJD",
				"source":"1"
			},
			{
				"time":"54373.215718",
				"band":"i'",
				"e_magnitude":"1.004",
				"magnitude":"23.574",
				"system":"SDSS",
				"telescope":"SDSS",
				"u_time":"MJD",
				"source":"1"
			},
			{
				"time":"54373.289765",
				"band":"r'",
				"e_magnitude":"0.465",
				"magnitude":"22.517",
				"system":"SDSS",
				"telescope":"SDSS",
				"u_time":"MJD",
				"source":"1"
			},
			{
				"time":"54373.290594",
				"band":"i'",
				"e_magnitude":"0.619",
				"magnitude":"22.629",
				"system":"SDSS",
				"telescope":"SDSS",
				"u_time":"MJD",
				"source":"1"
			},
			{
				"time":"54373.291424",
				"band":"u'",
				"e_magnitude":"2.153",
				"magnitude":"23.099",
				"system":"SDSS",
				"telescope":"SDSS",
				"u_time":"MJD",
				"source":"1"
			},
			{
				"time":"54373.292253",
				"band":"z'",
				"e_magnitude":"0.839",
				"magnitude":"22.487",
				"system":"SDSS",
				"telescope":"SDSS",
				"u_time":"MJD",
				"source":"1"
			},
			{
				"time":"54373.293082",
				"band":"g'",
				"e_magnitude":"1.733",
				"magnitude":"23.816",
				"system":"SDSS",
				"telescope":"SDSS",
				"u_time":"MJD",
				"source":"1"
			},
			{
				"time":"54379.225790",
				"band":"i'",
				"e_magnitude":"0.342",
				"magnitude":"22.344",
				"system":"SDSS",
				"telescope":"SDSS",
				"u_time":"MJD",
				"source":"1"
			},
			{
				"time":"54379.226620",
				"band":"u'",
				"e_magnitude":"0.688",
				"magnitude":"22.843",
				"system":"SDSS",
				"telescope":"SDSS",
				"u_time":"MJD",
				"source":"1"
			},
			{
				"time":"54379.227449",
				"band":"z'",
				"e_magnitude":"0.639",
				"magnitude":"22.197",
				"system":"SDSS",
				"telescope":"SDSS",
				"u_time":"MJD",
				"source":"1"
			},
			{
				"time":"54379.228278",
				"band":"g'",
				"e_magnitude":"0.335",
				"magnitude":"23.424",
				"system":"SDSS",
				"telescope":"SDSS",
				"u_time":"MJD",
				"source":"1"
			},
			{
				"time":"54381.227052",
				"band":"r'",
				"e_magnitude":"0.334",
				"magnitude":"22.565",
				"system":"SDSS",
				"telescope":"SDSS",
				"u_time":"MJD",
				"source":"1"
			},
			{
				"time":"54381.227882",
				"band":"i'",
				"e_magnitude":"1.086",
				"magnitude":"23.455",
				"system":"SDSS",
				"telescope":"SDSS",
				"u_time":"MJD",
				"source":"1"
			},
			{
				"time":"54381.228711",
				"band":"u'",
				"e_magnitude":"0.700",
				"magnitude":"22.536",
				"system":"SDSS",
				"telescope":"SDSS",
				"u_time":"MJD",
				"source":"1"
			},
			{
				"time":"54381.229540",
				"band":"z'",
				"e_magnitude":"0.530",
				"magnitude":"24.644",
				"system":"SDSS",
				"telescope":"SDSS",
				"u_time":"MJD",
				"source":"1"
			},
			{
				"time":"54381.230369",
				"band":"g'",
				"e_magnitude":"0.478",
				"magnitude":"23.113",
				"system":"SDSS",
				"telescope":"SDSS",
				"u_time":"MJD",
				"source":"1"
			},
			{
				"time":"54382.224293",
				"band":"r'",
				"e_magnitude":"0.298",
				"magnitude":"22.379",
				"system":"SDSS",
				"telescope":"SDSS",
				"u_time":"MJD",
				"source":"1"
			},
			{
				"time":"54382.225122",
				"band":"i'",
				"e_magnitude":"1.154",
				"magnitude":"23.478",
				"system":"SDSS",
				"telescope":"SDSS",
				"u_time":"MJD",
				"source":"1"
			},
			{
				"time":"54382.226780",
				"band":"z'",
				"e_magnitude":"0.713",
				"magnitude":"21.929",
				"system":"SDSS",
				"telescope":"SDSS",
				"u_time":"MJD",
				"source":"1"
			},
			{
				"time":"54382.227609",
				"band":"g'",
				"e_magnitude":"0.247",
				"magnitude":"22.764",
				"system":"SDSS",
				"telescope":"SDSS",
				"u_time":"MJD",
				"source":"1"
			},
			{
				"time":"54383.229742",
				"band":"r'",
				"e_magnitude":"0.451",
				"magnitude":"22.652",
				"system":"SDSS",
				"telescope":"SDSS",
				"u_time":"MJD",
				"source":"1"
			},
			{
				"time":"54383.230571",
				"band":"i'",
				"e_magnitude":"0.397",
				"magnitude":"22.068",
				"system":"SDSS",
				"telescope":"SDSS",
				"u_time":"MJD",
				"source":"1"
			},
			{
				"time":"54383.232229",
				"band":"z'",
				"e_magnitude":"1.113",
				"magnitude":"22.900",
				"system":"SDSS",
				"telescope":"SDSS",
				"u_time":"MJD",
				"source":"1"
			},
			{
				"time":"54383.233058",
				"band":"g'",
				"e_magnitude":"0.373",
				"magnitude":"23.007",
				"system":"SDSS",
				"telescope":"SDSS",
				"u_time":"MJD",
				"source":"1"
			},
			{
				"time":"54385.232239",
				"band":"r'",
				"e_magnitude":"0.289",
				"magnitude":"22.718",
				"system":"SDSS",
				"telescope":"SDSS",
				"u_time":"MJD",
				"source":"1"
			},
			{
				"time":"54385.233068",
				"band":"i'",
				"e_magnitude":"0.555",
				"magnitude":"23.023",
				"system":"SDSS",
				"telescope":"SDSS",
				"u_time":"MJD",
				"source":"1"
			},
			{
				"time":"54385.233898",
				"band":"u'",
				"e_magnitude":"0.791",
				"magnitude":"22.953",
				"system":"SDSS",
				"telescope":"SDSS",
				"u_time":"MJD",
				"source":"1"
			},
			{
				"time":"54385.234727",
				"band":"z'",
				"e_magnitude":"0.681",
				"magnitude":"22.305",
				"system":"SDSS",
				"telescope":"SDSS",
				"u_time":"MJD",
				"source":"1"
			},
			{
				"time":"54385.235556",
				"band":"g'",
				"e_magnitude":"0.193",
				"magnitude":"22.630",
				"system":"SDSS",
				"telescope":"SDSS",
				"u_time":"MJD",
				"source":"1"
			},
			{
				"time":"54386.226770",
				"band":"r'",
				"e_magnitude":"0.273",
				"magnitude":"22.515",
				"system":"SDSS",
				"telescope":"SDSS",
				"u_time":"MJD",
				"source":"1"
			},
			{
				"time":"54386.227600",
				"band":"i'",
				"e_magnitude":"0.556",
				"magnitude":"22.651",
				"system":"SDSS",
				"telescope":"SDSS",
				"u_time":"MJD",
				"source":"1"
			},
			{
				"time":"54386.229258",
				"band":"z'",
				"e_magnitude":"0.787",
				"magnitude":"22.697",
				"system":"SDSS",
				"telescope":"SDSS",
				"u_time":"MJD",
				"source":"1"
			},
			{
				"time":"54386.230087",
				"band":"g'",
				"e_magnitude":"0.251",
				"magnitude":"22.894",
				"system":"SDSS",
				"telescope":"SDSS",
				"u_time":"MJD",
				"source":"1"
			},
			{
				"time":"54388.230702",
				"band":"r'",
				"e_magnitude":"0.334",
				"magnitude":"22.697",
				"system":"SDSS",
				"telescope":"SDSS",
				"u_time":"MJD",
				"source":"1"
			},
			{
				"time":"54388.231531",
				"band":"i'",
				"e_magnitude":"0.397",
				"magnitude":"22.370",
				"system":"SDSS",
				"telescope":"SDSS",
				"u_time":"MJD",
				"source":"1"
			},
			{
				"time":"54388.232360",
				"band":"u'",
				"e_magnitude":"0.662",
				"magnitude":"22.565",
				"system":"SDSS",
				"telescope":"SDSS",
				"u_time":"MJD",
				"source":"1"
			},
			{
				"time":"54388.233189",
				"band":"z'",
				"e_magnitude":"0.733",
				"magnitude":"22.368",
				"system":"SDSS",
				"telescope":"SDSS",
				"u_time":"MJD",
				"source":"1"
			},
			{
				"time":"54388.234018",
				"band":"g'",
				"e_magnitude":"0.269",
				"magnitude":"22.969",
				"system":"SDSS",
				"telescope":"SDSS",
				"u_time":"MJD",
				"source":"1"
			},
			{
				"time":"54392.227573",
				"band":"i'",
				"e_magnitude":"0.322",
				"magnitude":"21.926",
				"system":"SDSS",
				"telescope":"SDSS",
				"u_time":"MJD",
				"source":"1"
			},
			{
				"time":"54392.228402",
				"band":"u'",
				"e_magnitude":"0.821",
				"magnitude":"22.509",
				"system":"SDSS",
				"telescope":"SDSS",
				"u_time":"MJD",
				"source":"1"
			},
			{
				"time":"54392.229232",
				"band":"z'",
				"e_magnitude":"0.804",
				"magnitude":"22.030",
				"system":"SDSS",
				"telescope":"SDSS",
				"u_time":"MJD",
				"source":"1"
			},
			{
				"time":"54392.230061",
				"band":"g'",
				"e_magnitude":"0.324",
				"magnitude":"22.699",
				"system":"SDSS",
				"telescope":"SDSS",
				"u_time":"MJD",
				"source":"1"
			},
			{
				"time":"54393.216164",
				"band":"r'",
				"e_magnitude":"0.296",
				"magnitude":"22.595",
				"system":"SDSS",
				"telescope":"SDSS",
				"u_time":"MJD",
				"source":"1"
			},
			{
				"time":"54393.216993",
				"band":"i'",
				"e_magnitude":"0.417",
				"magnitude":"22.536",
				"system":"SDSS",
				"telescope":"SDSS",
				"u_time":"MJD",
				"source":"1"
			},
			{
				"time":"54393.217822",
				"band":"u'",
				"e_magnitude":"0.358",
				"magnitude":"22.047",
				"system":"SDSS",
				"telescope":"SDSS",
				"u_time":"MJD",
				"source":"1"
			},
			{
				"time":"54393.218651",
				"band":"z'",
				"e_magnitude":"0.580",
				"magnitude":"22.247",
				"system":"SDSS",
				"telescope":"SDSS",
				"u_time":"MJD",
				"source":"1"
			},
			{
				"time":"54393.219480",
				"band":"g'",
				"e_magnitude":"0.338",
				"magnitude":"22.961",
				"system":"SDSS",
				"telescope":"SDSS",
				"u_time":"MJD",
				"source":"1"
			},
			{
				"time":"54394.215365",
				"band":"i'",
				"e_magnitude":"1.059",
				"magnitude":"22.738",
				"system":"SDSS",
				"telescope":"SDSS",
				"u_time":"MJD",
				"source":"1"
			},
			{
				"time":"54396.146163",
				"band":"r'",
				"e_magnitude":"0.499",
				"magnitude":"21.934",
				"system":"SDSS",
				"telescope":"SDSS",
				"u_time":"MJD",
				"source":"1"
			},
			{
				"time":"54396.146992",
				"band":"i'",
				"e_magnitude":"0.312",
				"magnitude":"21.149",
				"system":"SDSS",
				"telescope":"SDSS",
				"u_time":"MJD",
				"source":"1"
			},
			{
				"time":"54396.148650",
				"band":"z'",
				"e_magnitude":"0.514",
				"magnitude":"20.971",
				"system":"SDSS",
				"telescope":"SDSS",
				"u_time":"MJD",
				"source":"1"
			},
			{
				"time":"54396.149480",
				"band":"g'",
				"e_magnitude":"2.245",
				"magnitude":"25.686",
				"system":"SDSS",
				"telescope":"SDSS",
				"u_time":"MJD",
				"source":"1"
			},
			{
				"time":"54403.143504",
				"band":"r'",
				"e_magnitude":"0.181",
				"magnitude":"22.113",
				"system":"SDSS",
				"telescope":"SDSS",
				"u_time":"MJD",
				"source":"1"
			},
			{
				"time":"54403.144333",
				"band":"i'",
				"e_magnitude":"0.310",
				"magnitude":"22.200",
				"system":"SDSS",
				"telescope":"SDSS",
				"u_time":"MJD",
				"source":"1"
			},
			{
				"time":"54403.145162",
				"band":"u'",
				"e_magnitude":"0.286",
				"magnitude":"21.992",
				"system":"SDSS",
				"telescope":"SDSS",
				"u_time":"MJD",
				"source":"1"
			},
			{
				"time":"54403.145992",
				"band":"z'",
				"e_magnitude":"0.428",
				"magnitude":"21.482",
				"system":"SDSS",
				"telescope":"SDSS",
				"u_time":"MJD",
				"source":"1"
			},
			{
				"time":"54403.146821",
				"band":"g'",
				"e_magnitude":"0.191",
				"magnitude":"22.530",
				"system":"SDSS",
				"telescope":"SDSS",
				"u_time":"MJD",
				"source":"1"
			},
			{
				"time":"54404.143295",
				"band":"i'",
				"e_magnitude":"0.435",
				"magnitude":"22.531",
				"system":"SDSS",
				"telescope":"SDSS",
				"u_time":"MJD",
				"source":"1"
			},
			{
				"time":"54404.144124",
				"band":"u'",
				"e_magnitude":"0.372",
				"magnitude":"22.180",
				"system":"SDSS",
				"telescope":"SDSS",
				"u_time":"MJD",
				"source":"1"
			},
			{
				"time":"54404.144953",
				"band":"z'",
				"e_magnitude":"0.535",
				"magnitude":"21.542",
				"system":"SDSS",
				"telescope":"SDSS",
				"u_time":"MJD",
				"source":"1"
			},
			{
				"time":"54404.145783",
				"band":"g'",
				"e_magnitude":"0.183",
				"magnitude":"22.641",
				"system":"SDSS",
				"telescope":"SDSS",
				"u_time":"MJD",
				"source":"1"
			},
			{
				"time":"54406.136961",
				"band":"r'",
				"e_magnitude":"0.205",
				"magnitude":"22.224",
				"system":"SDSS",
				"telescope":"SDSS",
				"u_time":"MJD",
				"source":"1"
			},
			{
				"time":"54406.137790",
				"band":"i'",
				"e_magnitude":"0.392",
				"magnitude":"22.411",
				"system":"SDSS",
				"telescope":"SDSS",
				"u_time":"MJD",
				"source":"1"
			},
			{
				"time":"54406.138620",
				"band":"u'",
				"e_magnitude":"0.443",
				"magnitude":"22.412",
				"system":"SDSS",
				"telescope":"SDSS",
				"u_time":"MJD",
				"source":"1"
			},
			{
				"time":"54406.139449",
				"band":"z'",
				"e_magnitude":"0.804",
				"magnitude":"23.260",
				"system":"SDSS",
				"telescope":"SDSS",
				"u_time":"MJD",
				"source":"1"
			},
			{
				"time":"54406.140278",
				"band":"g'",
				"e_magnitude":"0.253",
				"magnitude":"22.924",
				"system":"SDSS",
				"telescope":"SDSS",
				"u_time":"MJD",
				"source":"1"
			},
			{
				"time":"54412.139017",
				"band":"r'",
				"e_magnitude":"0.312",
				"magnitude":"22.785",
				"system":"SDSS",
				"telescope":"SDSS",
				"u_time":"MJD",
				"source":"1"
			},
			{
				"time":"54412.139846",
				"band":"i'",
				"e_magnitude":"0.411",
				"magnitude":"22.579",
				"system":"SDSS",
				"telescope":"SDSS",
				"u_time":"MJD",
				"source":"1"
			},
			{
				"time":"54412.140675",
				"band":"u'",
				"e_magnitude":"0.324",
				"magnitude":"22.125",
				"system":"SDSS",
				"telescope":"SDSS",
				"u_time":"MJD",
				"source":"1"
			},
			{
				"time":"54412.141504",
				"band":"z'",
				"e_magnitude":"0.664",
				"magnitude":"22.520",
				"system":"SDSS",
				"telescope":"SDSS",
				"u_time":"MJD",
				"source":"1"
			},
			{
				"time":"54412.142333",
				"band":"g'",
				"e_magnitude":"0.201",
				"magnitude":"22.705",
				"system":"SDSS",
				"telescope":"SDSS",
				"u_time":"MJD",
				"source":"1"
			},
			{
				"time":"54416.134778",
				"band":"r'",
				"e_magnitude":"0.208",
				"magnitude":"22.290",
				"system":"SDSS",
				"telescope":"SDSS",
				"u_time":"MJD",
				"source":"1"
			},
			{
				"time":"54416.135607",
				"band":"i'",
				"e_magnitude":"0.552",
				"magnitude":"22.850",
				"system":"SDSS",
				"telescope":"SDSS",
				"u_time":"MJD",
				"source":"1"
			},
			{
				"time":"54416.136437",
				"band":"u'",
				"e_magnitude":"0.667",
				"magnitude":"22.983",
				"system":"SDSS",
				"telescope":"SDSS",
				"u_time":"MJD",
				"source":"1"
			},
			{
				"time":"54416.137266",
				"band":"z'",
				"e_magnitude":"0.613",
				"magnitude":"22.041",
				"system":"SDSS",
				"telescope":"SDSS",
				"u_time":"MJD",
				"source":"1"
			},
			{
				"time":"54416.138095",
				"band":"g'",
				"e_magnitude":"0.172",
				"magnitude":"22.588",
				"system":"SDSS",
				"telescope":"SDSS",
				"u_time":"MJD",
				"source":"1"
			},
			{
				"time":"54421.140072",
				"band":"r'",
				"e_magnitude":"1.053",
				"magnitude":"23.350",
				"system":"SDSS",
				"telescope":"SDSS",
				"u_time":"MJD",
				"source":"1"
			},
			{
				"time":"54421.140901",
				"band":"i'",
				"e_magnitude":"0.795",
				"magnitude":"22.841",
				"system":"SDSS",
				"telescope":"SDSS",
				"u_time":"MJD",
				"source":"1"
			},
			{
				"time":"54421.141730",
				"band":"u'",
				"e_magnitude":"0.533",
				"magnitude":"21.858",
				"system":"SDSS",
				"telescope":"SDSS",
				"u_time":"MJD",
				"source":"1"
			},
			{
				"time":"54421.142559",
				"band":"z'",
				"e_magnitude":"0.308",
				"magnitude":"20.844",
				"system":"SDSS",
				"telescope":"SDSS",
				"u_time":"MJD",
				"source":"1"
			},
			{
				"time":"54421.143388",
				"band":"g'",
				"e_magnitude":"0.768",
				"magnitude":"23.064",
				"system":"SDSS",
				"telescope":"SDSS",
				"u_time":"MJD",
				"source":"1"
			},
			{
				"time":"54423.131390",
				"band":"r'",
				"e_magnitude":"0.230",
				"magnitude":"21.590",
				"system":"SDSS",
				"telescope":"SDSS",
				"u_time":"MJD",
				"source":"1"
			},
			{
				"time":"54423.132219",
				"band":"i'",
				"e_magnitude":"0.451",
				"magnitude":"21.998",
				"system":"SDSS",
				"telescope":"SDSS",
				"u_time":"MJD",
				"source":"1"
			},
			{
				"time":"54423.133877",
				"band":"z'",
				"e_magnitude":"0.849",
				"magnitude":"23.598",
				"system":"SDSS",
				"telescope":"SDSS",
				"u_time":"MJD",
				"source":"1"
			},
			{
				"time":"54423.134706",
				"band":"g'",
				"e_magnitude":"0.669",
				"magnitude":"22.757",
				"system":"SDSS",
				"telescope":"SDSS",
				"u_time":"MJD",
				"source":"1"
			},
			{
				"time":"54425.132279",
				"band":"r'",
				"e_magnitude":"0.547",
				"magnitude":"22.432",
				"system":"SDSS",
				"telescope":"SDSS",
				"u_time":"MJD",
				"source":"1"
			},
			{
				"time":"54425.133108",
				"band":"i'",
				"e_magnitude":"0.330",
				"magnitude":"21.790",
				"system":"SDSS",
				"telescope":"SDSS",
				"u_time":"MJD",
				"source":"1"
			},
			{
				"time":"54425.133937",
				"band":"u'",
				"e_magnitude":"0.982",
				"magnitude":"22.080",
				"system":"SDSS",
				"telescope":"SDSS",
				"u_time":"MJD",
				"source":"1"
			},
			{
				"time":"54425.134766",
				"band":"z'",
				"e_magnitude":"0.839",
				"magnitude":"22.498",
				"system":"SDSS",
				"telescope":"SDSS",
				"u_time":"MJD",
				"source":"1"
			},
			{
				"time":"54431.143101",
				"band":"r'",
				"e_magnitude":"0.417",
				"magnitude":"22.024",
				"system":"SDSS",
				"telescope":"SDSS",
				"u_time":"MJD",
				"source":"1"
			},
			{
				"time":"54431.143930",
				"band":"i'",
				"e_magnitude":"0.503",
				"magnitude":"21.954",
				"system":"SDSS",
				"telescope":"SDSS",
				"u_time":"MJD",
				"source":"1"
			},
			{
				"time":"54431.144759",
				"band":"u'",
				"e_magnitude":"0.540",
				"magnitude":"21.044",
				"system":"SDSS",
				"telescope":"SDSS",
				"u_time":"MJD",
				"source":"1"
			},
			{
				"time":"54431.145588",
				"band":"z'",
				"e_magnitude":"1.225",
				"magnitude":"23.573",
				"system":"SDSS",
				"telescope":"SDSS",
				"u_time":"MJD",
				"source":"1"
			},
			{
				"time":"54431.146417",
				"band":"g'",
				"e_magnitude":"1.250",
				"magnitude":"22.700",
				"system":"SDSS",
				"telescope":"SDSS",
				"u_time":"MJD",
				"source":"1"
			},
			{
				"time":"54433.138323",
				"band":"r'",
				"e_magnitude":"0.210",
				"magnitude":"22.106",
				"system":"SDSS",
				"telescope":"SDSS",
				"u_time":"MJD",
				"source":"1"
			},
			{
				"time":"54433.139153",
				"band":"i'",
				"e_magnitude":"0.514",
				"magnitude":"22.466",
				"system":"SDSS",
				"telescope":"SDSS",
				"u_time":"MJD",
				"source":"1"
			},
			{
				"time":"54433.139982",
				"band":"u'",
				"e_magnitude":"0.413",
				"magnitude":"22.100",
				"system":"SDSS",
				"telescope":"SDSS",
				"u_time":"MJD",
				"source":"1"
			},
			{
				"time":"54433.140811",
				"band":"z'",
				"e_magnitude":"0.641",
				"magnitude":"21.641",
				"system":"SDSS",
				"telescope":"SDSS",
				"u_time":"MJD",
				"source":"1"
			},
			{
				"time":"54433.141640",
				"band":"g'",
				"e_magnitude":"0.164",
				"magnitude":"22.295",
				"system":"SDSS",
				"telescope":"SDSS",
				"u_time":"MJD",
				"source":"1"
			}
		]
	}
}